openyieldtables/__init__.py
openyieldtables/classes/__init__.py
openyieldtables/classes/data_management.py
openyieldtables/data/yield_tables.csv
openyieldtables/data/yield_tables_meta.csv
openyieldtables/models/__init__.py
openyieldtables/models/yieldtable.py
openyieldtables/py.typed
openyieldtables/utils/__init__.py
openyieldtables/utils/utils.py
openyieldtables/yieldtables.py
openyieldtables-2.68.1.dist-info/LICENSE
openyieldtables-2.68.1.dist-info/METADATA
openyieldtables-2.68.1.dist-info/WHEEL
openyieldtables-2.68.1.dist-info/RECORD
