Metadata-Version: 2.1
Name: openyieldtables
Version: 2.68.1
Summary: 
Home-page: https://github.com/treely/openyieldtables
License: MIT
Author: Tree.ly
Author-email: hello@tree.ly
Maintainer: FMM
Maintainer-email: fmm@fmm.at
Requires-Python: >=3.9,<4.0
Classifier: License :: OSI Approved :: MIT License
Classifier: Programming Language :: Python :: 3
Classifier: Programming Language :: Python :: 3.9
Classifier: Programming Language :: Python :: 3.10
Classifier: Programming Language :: Python :: 3.11
Classifier: Programming Language :: Python :: 3.12
Requires-Dist: pandas (>=2.2.1,<3.0.0)
Requires-Dist: pydantic (>=2.6.4,<3.0.0)
Project-URL: Documentation, https://openyieldtables.readthedocs.io
Project-URL: Repository, https://github.com/treely/openyieldtables
